{
"ID": "41",
"University": "Bangladesh University of Engineering and Technology"
}

{
"ID": "229",
"University": "University of Dhaka"
}

{
"ID": "125",
"University": "Jahangirnagar University"
}

{
"ID": "590",
"University": "Shahjalal University of Science and Technology"
}

{
"ID": "824",
"University": "Khulna University of Engineering & Technology"
}

{
"ID": "1443",
"University": "American International University - Bangladesh"
}

{
"ID": "865",
"University": "Islamic University of Technology"
}

{
"ID": "2795",
"University": "Rajshahi University of Engineering & Technology"
}

{
"ID": "917",
"University": "Chittagong University of Engineering &"
}

